{
  "_id": "542ed0142df9c20401f53dcc",
  "application": {
    "base": "https://:subdomain.salesforce.com/services/data/v20.0",
    "resources": [
      {
        "path": "/query",
        "displayName": "/query",
        "doc": {
          "url": "GET https://:subdomain.salesforce.com/services/data/v20.0/query"
        },
        "httpMethod": "GET",
        "curl": "curl -X",
        "params": [
          {
            "name": "q",
            "style": "query",
            "type": "string",
            "displayName": "Query",
            "required": true,
            "default": ""
          },
          {
            "name": ":subdomain",
            "displayName": "Subdomain",
            "style": "url",
            "type": "string",
            "required": true,
            "default": "na1"
          }
        ],
        "url": "https://:subdomain.salesforce.com/services/data/v20.0/query"
      }
    ]
  },
  "oauth":{
    "development": {
      "clientID":     "INSERT_SECERT_HERE",
      "clientSecret": "INSERT_SECERT_HERE",
      "callbackURL":    "http://localhost:8080/api/oauth/salesforce/callback",
      "tokenMethod": "access_token_bearer"
    },
    "production": {
      "clientID":     "INSERT_SECERT_HERE",
      "clientSecret": "INSERT_SECERT_HERE",
      "callbackURL":    "https://app.octoblu.com/api/oauth/salesforce/callback",
      "tokenMethod": "access_token_bearer"
    },
    "staging": {
      "clientID":     "INSERT_SECERT_HERE",
      "clientSecret": "INSERT_SECERT_HERE",
      "callbackURL":    "https://staging.octoblu.com/api/oauth/salesforce/callback",
      "tokenMethod": "access_token_bearer"
    }
  },
  "auth_strategy": "oauth",
  "documentation": "https://www.salesforce.com/us/developer/docs/api_rest",
  "enabled": true,
  "name": "SalesForce",
  "isPassport": true,
  "type": "channel:salesforce"
}
